AUTHORS.md
MANIFEST.in
README.md
requirements.txt
setup.py
config/accounts.cfg
config/api_keys.cfg
config/browser.cfg
config/general.cfg
config/plugins/wrapper.py.sample
config/plugins/wrapper_v2.py.sample
doc/CHANGES.md
doc/FAQ.md
doc/HACKING.md
doc/INSTALL.md
osrframework/__init__.py
osrframework/alias_generator.py
osrframework/checkfy.py
osrframework/domainfy.py
osrframework/launcher.py
osrframework/mailfy.py
osrframework/phonefy.py
osrframework/searchfy.py
osrframework/upgrade.py
osrframework/usufy.py
osrframework.egg-info/PKG-INFO
osrframework.egg-info/SOURCES.txt
osrframework.egg-info/dependency_links.txt
osrframework.egg-info/entry_points.txt
osrframework.egg-info/requires.txt
osrframework.egg-info/top_level.txt
osrframework/api/__init__.py
osrframework/api/twitter_api.py
osrframework/domains/__init__.py
osrframework/domains/brand_tld.py
osrframework/domains/cctld.py
osrframework/domains/email_providers.py
osrframework/domains/generic_tld.py
osrframework/domains/geographic_tld.py
osrframework/domains/gtld.py
osrframework/domains/other_subdomains.py
osrframework/searchengines/__init__.py
osrframework/searchengines/google.py
osrframework/thirdparties/__init__.py
osrframework/thirdparties/checkIfHashIsCracked.py
osrframework/thirdparties/checkIpDetails.py
osrframework/thirdparties/checkIpFromAlias.py
osrframework/thirdparties/checkPhoneDetails.py
osrframework/thirdparties/getBitcoinAddressDetails.py
osrframework/thirdparties/blockchain_info/__init__.py
osrframework/thirdparties/blockchain_info/getBitcoinAddressDetails.py
osrframework/thirdparties/dehashed_com/__init__.py
osrframework/thirdparties/dehashed_com/dehashed.py
osrframework/thirdparties/duckduckgo_com/__init__.py
osrframework/thirdparties/duckduckgo_com/duckduckgo.py
osrframework/thirdparties/haveibeenpwned_com/__init__.py
osrframework/thirdparties/haveibeenpwned_com/hibp.py
osrframework/thirdparties/infobel_com/__init__.py
osrframework/thirdparties/infobel_com/checkPhoneDetails.py
osrframework/thirdparties/infobel_com/processing.py
osrframework/thirdparties/ip_api_com/__init__.py
osrframework/thirdparties/ip_api_com/checkIpDetails.py
osrframework/thirdparties/md5crack_com/__init__.py
